flask_sendmail/__init__.py
flask_sendmail/connection.py
flask_sendmail/mail.py
flask_sendmail/message.py
Flask_Sendmail_ng-0.3.dist-info/LICENSE
Flask_Sendmail_ng-0.3.dist-info/METADATA
Flask_Sendmail_ng-0.3.dist-info/WHEEL
Flask_Sendmail_ng-0.3.dist-info/top_level.txt
Flask_Sendmail_ng-0.3.dist-info/RECORD
