Metadata-Version: 2.1
Name: Flask-Sendmail-ng
Version: 0.3
Summary: Flask extension for sendmail
Home-page: http://github.com/ncrocfer/flask-sendmail-ng
Author: Anthony Ford
Author-email: ford.anthonyj@gmail.com
License: BSD
Platform: any
Classifier: Development Status :: 4 - Beta
Classifier: Environment :: Web Environment
Classifier: Intended Audience :: Developers
Classifier: License :: OSI Approved :: BSD License
Classifier: Operating System :: OS Independent
Classifier: Programming Language :: Python
Classifier: Topic :: Internet :: WWW/HTTP :: Dynamic Content
Classifier: Topic :: Software Development :: Libraries :: Python Modules
Requires-Dist: Flask
